swan/__init__.py
swan/api_client.py
swan/session.py
swan/api/__init__.py
swan/api/bucket_api.py
swan/api/orchestrator.py
swan/common/__init__.py
swan/common/constant.py
swan/common/exception.py
swan/common/params.py
swan/common/utils.py
swan/contract/__init__.py
swan/contract/swan_contract.py
swan/contract/abi/ClientPayment.json
swan/contract/abi/CollectionFactory.json
swan/contract/abi/ERC20.json
swan/contract/abi/PaymentContract.json
swan/contract/abi/SwanPayment.json
swan/contract/abi/SwanToken.json
swan/object/__init__.py
swan/object/bucket_storage.py
swan/object/cp_config.py
swan/object/models.py
swan/object/onchain_storage.py
swan/object/task_spec.py
swan_sdk-0.1.4.dist-info/LICENSE
swan_sdk-0.1.4.dist-info/METADATA
swan_sdk-0.1.4.dist-info/WHEEL
swan_sdk-0.1.4.dist-info/top_level.txt
swan_sdk-0.1.4.dist-info/RECORD
