Metadata-Version: 2.1
Name: swan-sdk
Version: 0.1.4
Summary: A python developer tool kit for Swan services.
Home-page: https://github.com/swanchain/python-swan-sdk
Author: SwanCloud
Author-email: swan.development@nbai.io
License: MIT
Classifier: License :: OSI Approved :: MIT License
Classifier: Programming Language :: Python :: 3
License-File: LICENSE
Requires-Dist: requests ==2.28.1
Requires-Dist: web3 ==6.20.3
Requires-Dist: requests-toolbelt ==1.0.0
Requires-Dist: tqdm ==4.66.5
